[
  {
    "filename": "2026-06-07-00-43-18_AI.md",
    "subject": "AI",
    "title": "temp notes",
    "tags": [
      "machine learning",
      "classification",
      "natural language processing",
      "reinforcement learning",
      "model evaluation"
    ],
    "urls": [],
    "word_count": 43,
    "created": "2026-06-07-00-43-18",
    "last_edited": "2026-06-07-00-43-18",
    "ingested": true
  },
  {
    "filename": "2026-06-28-13-54-47_Java.md",
    "subject": "Java",
    "title": "byte_code",
    "tags": [
      "Introduction to Java class and object",
      "Creating multiple threads",
      "synchronization",
      "Byte-code",
      "JVM"
    ],
    "urls": [],
    "word_count": 53,
    "created": "2026-06-28-13-54-47",
    "last_edited": "2026-06-28-13-54-47",
    "ingested": false
  }
]